apito/__init__.py
apito/aioclient.py
apito/client.py
apito/models/__init__.py
apito/models/phone.py
apito/models/search.py
apito-0.4.3.dist-info/LICENSE
apito-0.4.3.dist-info/METADATA
apito-0.4.3.dist-info/WHEEL
apito-0.4.3.dist-info/top_level.txt
apito-0.4.3.dist-info/RECORD
