Metadata-Version: 2.1
Name: apito
Version: 0.4.3
Summary: Avito API interaction tool 
Home-page: https://github.com/WhiteApfel/apito
Author: WhiteApfel
Author-email: white@pfel.ru
License: MPL 2.0
Project-URL: Donate, https://pfel.cc/donate
Project-URL: Source, https://github.com/WhiteApfel/apito
Project-URL: Telegram, https://t.me/apfel
Keywords: Avito API Wrapper Parser Авито АПИ парсер
Platform: UNKNOWN
License-File: LICENSE
Requires-Dist: httpx (~=0.18.2)
Requires-Dist: typing (~=3.7.4.3)
Requires-Dist: pydantic (~=1.8.2)
Requires-Dist: httpx-socks[asyncio] (~=0.4.1)
